pylithium
