Metadata-Version: 1.0
Name: pylithiumsso
Version: 0.2.2
Summary: Python Client for Lithium SSO Integration
Home-page: https://github.com/jawbone/pylithiumsso
Author: Alex Milstead
Author-email: amilstead@jawbone.com
License: MIT
Platform: UNKNOWN
